limeinstall/_API.py
limeinstall/__init__.py
limeinstall/__main__.py
limeinstall-0.1.0.dist-info/licenses/LICENSE.txt
limeinstall-0.1.0.dist-info/METADATA
limeinstall-0.1.0.dist-info/WHEEL
limeinstall-0.1.0.dist-info/entry_points.txt
limeinstall-0.1.0.dist-info/top_level.txt
limeinstall-0.1.0.dist-info/RECORD
