Metadata-Version: 2.4
Name: limeinstall
Version: 0.1.0
Summary: Repository installation tool
Author: Limespy
Project-URL: Homepage, https://github.com/Limespy/Limeinstaller
Project-URL: Changelog, https://github.com/Limespy/Limeinstaller/blob/main/README.md#Changelog
Project-URL: Issue Tracker, https://github.com/Limespy/Limeinstaller/issues
Classifier: Development Status :: 3 - Alpha
Classifier: License :: OSI Approved :: MIT License
Classifier: Operating System :: Microsoft :: Windows
Classifier: Operating System :: POSIX
Classifier: Operating System :: Unix
Classifier: Programming Language :: Python :: 3
Classifier: Programming Language :: Python :: 3 :: Only
Classifier: Programming Language :: Python :: 3.11
Classifier: Programming Language :: Python :: 3.12
Classifier: Programming Language :: Python :: 3.13
Classifier: Programming Language :: Python :: 3.14
Requires-Python: >=3.11
License-File: LICENSE.txt
Requires-Dist: pip>=25
Provides-Extra: build
Requires-Dist: limedev[build]>=0.6.0; extra == "build"
Provides-Extra: dev
Requires-Dist: limedev[package,readme,test]>=0.6.1; extra == "dev"
Requires-Dist: pre-commit<4,>=3.2.2; extra == "dev"
Requires-Dist: tox>=4.5.1; extra == "dev"
Requires-Dist: tox-uv>=1.25; extra == "dev"
Provides-Extra: test-functional
Requires-Dist: pytest>=7.2.0; extra == "test-functional"
Dynamic: license-file
